ai_changelog/__init__.py
ai_changelog/__main__.py
ai_changelog/pydantic_models.py
ai_changelog/string_templates.py
ai_changelog/utils.py
ai_changelog-0.0.14.dist-info/LICENSE
ai_changelog-0.0.14.dist-info/METADATA
ai_changelog-0.0.14.dist-info/WHEEL
ai_changelog-0.0.14.dist-info/entry_points.txt
ai_changelog-0.0.14.dist-info/top_level.txt
ai_changelog-0.0.14.dist-info/RECORD
