Metadata-Version: 2.1
Name: ai-changelog
Version: 0.0.14
Summary: A Python project that generates AI-based changelogs.
Author: Joshua Sundance Bailey
License: MIT License
Project-URL: Homepage, https://github.com/joshuasundance-swca/ai_changelog
Keywords: langchain,changelog,github,openai,developer-tools,documentation
Classifier: License :: OSI Approved :: MIT License
Classifier: Programming Language :: Python
Classifier: Programming Language :: Python :: 3
Requires-Python: >=3.7
License-File: LICENSE
Requires-Dist: langchain
Requires-Dist: openai
Requires-Dist: pydantic
Provides-Extra: dev
Requires-Dist: pre-commit ; extra == 'dev'
Requires-Dist: bumpver ; extra == 'dev'
